NRlabdtsc/NRlab.py
NRlabdtsc/NRutils.py
NRlabdtsc/__init__.py
NRlabdtsc-1.0.0.dist-info/LICENSE
NRlabdtsc-1.0.0.dist-info/METADATA
NRlabdtsc-1.0.0.dist-info/WHEEL
NRlabdtsc-1.0.0.dist-info/entry_points.txt
NRlabdtsc-1.0.0.dist-info/top_level.txt
NRlabdtsc-1.0.0.dist-info/RECORD
