Metadata-Version: 2.1
Name: NRlabdtsc
Version: 1.0.0
Summary: This tool is intended for training in waveform generation of the fifth generation new radio (5GNR). 
Home-page: https://github.com/guipalloz/NRlab-dtsc
Author: Guillermo Palomino Lozano
Author-email: jabecerra@us.es
License: MIT
Platform: UNKNOWN
Classifier: License :: OSI Approved :: MIT License
Classifier: Programming Language :: Python :: 3
Classifier: Programming Language :: Python :: 3.7
Requires-Dist: feedparser
Requires-Dist: html2text
